[
    {
        "id": "gmb_qr_minimal_premium_v2",
        "name": "Minimal Premium Poster",
        "description": "Clean, modern layout inspired by Balaji Electronics poster.",
        "orientation": "portrait",
        "dimensions": {
            "width": 2480,
            "height": 3508
        },
        "elements": [
            {
                "id": "top-logo",
                "type": "logo",
                "x": 1240,
                "y": 450,
                "maxWidth": 800,
                "maxHeight": 450
            },
            {
                "id": "stars",
                "type": "star-rating",
                "x": 1240,
                "y": 850,
                "size": 110,
                "color": "#FFC107",
                "count": 5
            },
            {
                "id": "hook",
                "type": "text",
                "content": "Loved our service?",
                "field": "hookText",
                "x": 1240,
                "y": 1050,
                "fontSize": 140,
                "fontFamily": "Inter, sans-serif",
                "fontWeight": "500",
                "align": "center",
                "color": "#333333"
            },
            {
                "id": "main-qr",
                "type": "qr",
                "x": 1240,
                "y": 2000,
                "size": 1300,
                "errorCorrection": "H",
                "includeLogo": true,
                "logoPadding": 40,
                "logoShape": "circle"
            },
            {
                "id": "cta",
                "type": "text",
                "content": "Scan to leave a Google review",
                "x": 1240,
                "y": 2850,
                "fontSize": 80,
                "fontFamily": "Inter, sans-serif",
                "align": "center",
                "color": "#333333"
            },
            {
                "id": "google-branding",
                "type": "text",
                "content": "Google Reviews",
                "x": 1240,
                "y": 3050,
                "fontSize": 100,
                "fontFamily": "Inter, sans-serif",
                "fontWeight": "500",
                "align": "center",
                "color": "#5F6368"
            }
        ]
    },
    {
        "id": "dental-special-v1",
        "name": "Dental Clinic Style",
        "description": "Inspired by modern clinic review posters with search bar branding.",
        "orientation": "portrait",
        "dimensions": {
            "width": 2480,
            "height": 3508
        },
        "elements": [
            {
                "id": "dental-logo",
                "type": "logo",
                "x": 1240,
                "y": 450,
                "maxWidth": 1000,
                "maxHeight": 500
            },
            {
                "id": "dental-thanks",
                "type": "text",
                "content": "thanks for your business!",
                "field": "hookText",
                "x": 1240,
                "y": 850,
                "fontSize": 140,
                "fontFamily": "cursive, serif",
                "align": "center",
                "color": "#333333"
            },
            {
                "id": "dental-impressed",
                "type": "text",
                "content": "Impressed with our services?",
                "field": "ctaText",
                "x": 1240,
                "y": 1050,
                "fontSize": 80,
                "fontFamily": "Inter, sans-serif",
                "fontWeight": "bold",
                "align": "center",
                "color": "#009DAE"
            },
            {
                "id": "dental-qr",
                "type": "qr",
                "x": 1240,
                "y": 1900,
                "size": 1100,
                "errorCorrection": "H"
            },
            {
                "id": "search-bar-border",
                "type": "decoration",
                "x": 340,
                "y": 2700,
                "width": 1800,
                "height": 180,
                "color": "#ffffff",
                "borderRadius": 90,
                "borderWidth": 8,
                "strokeColor": "#000000"
            },
            {
                "id": "search-bar-text",
                "type": "text",
                "field": "businessName",
                "content": "Your Business Name",
                "x": 1240,
                "y": 2795,
                "fontSize": 85,
                "fontFamily": "Inter, sans-serif",
                "align": "center",
                "color": "#333333"
            },
            {
                "id": "footer-text",
                "type": "text",
                "content": "Give us a review",
                "x": 800,
                "y": 3150,
                "fontSize": 100,
                "fontFamily": "Georgia, serif",
                "fontWeight": "bold",
                "align": "center",
                "color": "#000000"
            },
            {
                "id": "footer-stars",
                "type": "star-rating",
                "x": 1800,
                "y": 3145,
                "size": 100,
                "color": "#F4C430",
                "count": 5
            }
        ]
    },
    {
        "id": "google-review-dark-executive",
        "name": "Dark Executive Card",
        "description": "Premium dark-themed Google search result style card.",
        "orientation": "portrait",
        "dimensions": {
            "width": 2480,
            "height": 3508
        },
        "elements": [
            {
                "id": "main-bg",
                "type": "decoration",
                "x": 0,
                "y": 0,
                "width": 2480,
                "height": 3508,
                "color": "#111111"
            },
            {
                "id": "top-circle",
                "type": "decoration",
                "x": 1040,
                "y": -200,
                "width": 400,
                "height": 400,
                "color": "#111111",
                "borderRadius": 200
            },
            {
                "id": "user-icon",
                "type": "logo",
                "x": 1240,
                "y": 50,
                "maxWidth": 150,
                "maxHeight": 150
            },
            {
                "id": "google-red-square",
                "type": "decoration",
                "x": 1850,
                "y": 300,
                "width": 250,
                "height": 250,
                "color": "#EA4335",
                "borderRadius": 40
            },
            {
                "id": "google-g-white",
                "type": "text",
                "content": "G",
                "x": 1975,
                "y": 480,
                "fontSize": 180,
                "fontFamily": "Inter, sans-serif",
                "fontWeight": "bold",
                "align": "center",
                "color": "#ffffff"
            },
            {
                "id": "header-title",
                "type": "text",
                "content": "Google Review",
                "x": 300,
                "y": 450,
                "fontSize": 140,
                "fontFamily": "Inter, sans-serif",
                "fontWeight": "bold",
                "align": "left",
                "color": "#ffffff"
            },
            {
                "id": "rating-score",
                "type": "text",
                "content": "5.0 Excellent",
                "x": 300,
                "y": 680,
                "fontSize": 200,
                "fontFamily": "Inter, sans-serif",
                "fontWeight": "bold",
                "align": "left",
                "color": "#ffffff"
            },
            {
                "id": "reviewer-name",
                "type": "text",
                "content": "Reviewed by Your Business",
                "field": "businessName",
                "x": 300,
                "y": 920,
                "fontSize": 80,
                "fontFamily": "Inter, sans-serif",
                "align": "left",
                "color": "#ffffff"
            },
            {
                "id": "section-divider",
                "type": "decoration",
                "x": 300,
                "y": 1050,
                "width": 1880,
                "height": 6,
                "color": "#ffffff"
            },
            {
                "id": "review-quote",
                "type": "text",
                "content": "The service was outstanding! Highly recommend to everyone. Will definitely come back again, Thank you so much!",
                "field": "hookText",
                "x": 300,
                "y": 1250,
                "fontSize": 75,
                "fontFamily": "Inter, sans-serif",
                "align": "left",
                "color": "#ffffff",
                "lineHeight": 1.4
            },
            {
                "id": "qr-white-frame",
                "type": "decoration",
                "x": 640,
                "y": 1750,
                "width": 1200,
                "height": 1200,
                "color": "#ffffff",
                "borderRadius": 120
            },
            {
                "id": "google-qr",
                "type": "qr",
                "x": 1240,
                "y": 2350,
                "size": 1000,
                "errorCorrection": "H"
            }
        ]
    }
]